<odoo>
    <record id="view_partner_form_inherit_reservation_cash_stats" model="ir.ui.view">
        <field name="name">res.partner.form.reservation.cash.stats</field>
        <field name="model">res.partner</field>
        <field name="inherit_id" ref="base.view_partner_form"/>
        <field name="arch" type="xml">
            <xpath expr="//div[@name='button_box']" position="inside">
                <button name="action_view_partner_cash_ins" type="object" class="oe_stat_button" icon="fa-money">
                    <field name="cash_in_stat_display" widget="statinfo" string="Total encaissé"/>
                </button>
                <button name="action_view_partner_reservations" type="object" class="oe_stat_button" icon="fa-archive">
                    <field name="reservation_stat_display" widget="statinfo" string="Total réservé"/>
                </button>
                <button name="action_view_partner_reservation_transfers" type="object" class="oe_stat_button" icon="fa-exchange">
                    <field name="reservation_transfer_count" widget="statinfo" string="Transferts réservation"/>
                </button>
            </xpath>
        </field>
    </record>
</odoo>
